# 方法调用

**方法调用不等同于方法执行** ，方法调用阶段的唯一任务就是 **确定被调用方法的版本**（即调用哪一个方法），暂时还不涉及方法内部的具体运行过程。Class文件的编译过程中不包括传统编译器中的连接步骤，一切方法调用在Class文件里面存储的都是符号引用，而不是方法在实际运行时内存布局中的入口地址（直接引用）。所以需要在类加载阶段，甚至到运行期才能确定目标方法的直接引用。

所有的方法调用中的目标方法在Class文件里面都是一个常量池中的符号引用，在类加载阶段，会将其中的一部分符号引用转化为直接引用，这种解析能成立的前提是：**方法在程序真正运行之前就有一个可确定的调用版本，并且这个方法的调用版本在运行期间是不可变的**。也就是说，调用目标在程序代码写好、编译器进行编译时就必须确定下来，这类方法的调用成为解析(Resolution)。

JAVA中符号“编译器可知、运行期不可变”的方法包括：静态方法、私有方法两大类。前者与类型直接关联，后者在外部不可被访问，这就决定了他们都不可能通过继承或别的方式重写其版本。因此都适合在类的加载阶段进行解析。

JAVA虚拟机里面提供了5条方法调用字节码指令。分别如下：

     * invokestatic:调用静态方法
     * invokespecial:调用实例构造器<init>方法、私有方法和父类方法（super(),super.method()）。
     * invokevirtual:调用所有的虚方法。
     * invokeinterface:调用接口方法，会在运行时期再确定一个实现此接口的对象。
     * invokedynamic:现在运行时期动态解析出调用点限定符所引用的方法，然后再执行该方法，在此之前的4条指令，分派逻辑都是固化在虚拟机里面的，而invokedynamic指令的分派逻辑是由用户所设定的引导方法决定的。

只要能被invokestatic和invokespecial指令调用的方法都可以在解析阶段中确定唯一的调用版本，符合这个条件的有静态方法、私有方法、实例构造器、父类方法4类，它们在类加载阶段就会把符号引用解析为该方法的直接引用。这些方法称为非虚方法

其他方法(除去final方法)称为虚方法

final方法虽然是使用invokevirtual指令调用，因为final方法注定不会被重写，也就是无法被覆盖，也就无需对其进行多态选择.在java语言规范中说明了final方法是一种非虚方法.

解析调用一定是一个静态的过程，在编译期间就可以完全确定，在类装载的解析阶段就会把涉及的符号引用全部转化为可确定的直接引用，不会延迟到运行期去完成。
分派调用可能是静态的也可能是动态的，根据分派一句的宗量数可分为单分派和多分派。因此分派可分为：静态单分派、静态多分派、动态单分派、动态多分派。

## 解析调用的方法种类

* 静态方法
* 私有方法
* 实例构造器
* 父类方法
* final方法

# 分派 Dispatch

## 静态分派(方法重载)

严格来说,Dispatch这个词一般不用在静态环境中,**英文文档的称呼为 Method Overload Resolution**

### 静态类型(Static Type)和实际类型(Actual Type)

Human man = new Man();

Human成为变量man的静态类型，或者叫做外观类型(Apparent Type)

Man则称为变量的实际类型

静态类型和实际类型在程序中都可以发生一些变化，区别是静态类型的变化仅仅在使用时发生（比如强制类型转换），变量本身的静态类型不会改变，并且 **最终的静态类型在编译器就是可知的**；而 **实际类型变化的结果在运行期才可以确定**，编译器在编译程序的时候并不知道一个对象的实际类型是什么

比如如下代码：
```java
    //实际类型变化
    Human man = new Man();
    Human woman = new Woman();
    //通过强转实现静态类型变化
    sr.sayHello((Man)man);
    sr.sayHello((Woman)woman);
```

### 重载是通过参数的静态类型来作为判断依据的

```java
public class StaticDispatch {
    static abstract class Human{

    }
    static class Man extends Human{

    }
    static class Woman extends  Human{

    }
    @Test
    public void test(){
        Human man = new Man();
        Human woman = new Woman();
        StaticDispatch sr = new StaticDispatch();
        sr.sayHello(man);
        sr.sayHello(woman);

    }


    public void sayHello(Human guy){
        System.out.println("Hello guy");
    }
    public void sayHello(Man guy){
        System.out.println("Hello man");
    }
    public void sayHello(Woman guy){
        System.out.println("Hello woman");
    }
}
```

运行结果为
```java
Hello guy
Hello guy
```

虚拟机（编译器）在确定重载函数版本时是通过参数的静态类型而不是实际类型作为判定依据。因此，在编译阶段，编译器就可以根据静态类型确定使用哪个重载的版本。

所有依赖静态类型来定位方法执行版本的分派动作称为静态分派.**静态分派的典型应用是方法重载**.

**静态分派发生在编译阶段**,因此确定静态分派的动作实际上不上有虚拟机来执行的.

编译器虽然能确定出方法的重载版本，但在很多情况下这个重载版本并不是“唯一的”，往往只能确定一个“更加合适的”版本。产生这种模糊结论的主要原因是 **字面量不需要定义**，所以字面量没有显式的静态类型，它的静态类型只能通过语言上的规则去理解和推断

假设我们的参数类型为char，那么我们重载的优先级为：

char
int
long
float
double
Character
Serializable
Object
char...

不会匹配到byte和short类型的重载是因为char到byte或short是不安全的

## 动态分派

我们把在运行期根据实际类型确定方法执行版本的分派叫做动态分派

与多态性的另一个体现"重写(Override)"有着很密切的联系

```java
public class StaticDispatch {

        static abstract class Humnan {
            abstract void sayHello();
        }
        static class Man extends Humnan {
            @Override
            void sayHello() {
                System.out.println("hello, i'm Man");
            }
        }
        static class Woman extends Humnan {
            @Override
            void sayHello() {
                System.out.println("hello, i'm Woman");
            }
        }

        public static void main(String[] args) {
            Humnan man = new Man();
            Humnan woman = new Woman();
            man.sayHello();
            woman.sayHello();
            man = new Woman();
            man.sayHello();
        }

}
```

```java
public static void main(java.lang.String[]);
    Code:
       0: new           #2                  // class tests/StaticDispatch$Man
       3: dup
       4: invokespecial #3                  // Method tests/StaticDispatch$Man."<init>":()V
       7: astore_1
       8: new           #4                  // class tests/StaticDispatch$Woman
      11: dup
      12: invokespecial #5                  // Method tests/StaticDispatch$Woman."<init>":()V
      15: astore_2
      16: aload_1
      17: invokevirtual #6                  // Method tests/StaticDispatch$Humnan.sayHello:()V
      20: aload_2
      21: invokevirtual #6                  // Method tests/StaticDispatch$Humnan.sayHello:()V
      24: new           #4                  // class tests/StaticDispatch$Woman
      27: dup
      28: invokespecial #5                  // Method tests/StaticDispatch$Woman."<init>":()V
      31: astore_1
      32: aload_1
      33: invokevirtual #6                  // Method tests/StaticDispatch$Humnan.sayHello:()V
      36: return
```

字节码0 ~ 15行对应以下代码

```java
Humnan man = new Man();
Humnan woman = new Woman();
```

字节码16~21行是关键部分

16和20两句分别把刚刚创建的两个对象的引用压到栈顶,这两个对象是将要执行的sayHello方法的所有者,称为接受者(Receiver).

17和21行指令进行方法调用。这两天指令单从字节码角度来看,无论是指令(都是invokevirtual)还是参数(都是常量池中第22项的常量,注释显示了这个常量是Human.sayHello()的符号引用)都是完全引用的,但是最终执行的目标方法并不相同.

这得从invokevirtual指令的多态查找说起了，invokevirtual指令在运行时分为以下几个步骤：

* 找到操作数栈的栈顶元素所指向的对象的实际类型，记为C；
* 如果C中存在描述符和简单名称都相符的方法，则进行访问权限验证，如果验证通过，则直接返回这个方法的直接引用，否则返回java.lang.IllegalAccessError异常；
* 如果C中不存在对应的方法，则按照继承关系对C的各个父类进行第2步的操作；
* 如果各个父类也没对应的方法，则返回异常；

由于invokevirtual指令第一步就是在运行期确定接收者的实际类型,所以两次调用中的invokevirtual指令把常量池中的类方法符号引用解析到了不同的直接引用上

这个过程就是Java语言中重写的本质。

```java

```
```java

```
```java

```








































#
